odoo/addons/sale_stock_release_channel/README.rst
odoo/addons/sale_stock_release_channel/__init__.py
odoo/addons/sale_stock_release_channel/__manifest__.py
odoo/addons/sale_stock_release_channel/i18n/it.po
odoo/addons/sale_stock_release_channel/i18n/sale_stock_release_channel.pot
odoo/addons/sale_stock_release_channel/models/__init__.py
odoo/addons/sale_stock_release_channel/models/sale_order.py
odoo/addons/sale_stock_release_channel/models/stock_picking.py
odoo/addons/sale_stock_release_channel/readme/CONTRIBUTORS.md
odoo/addons/sale_stock_release_channel/readme/DESCRIPTION.md
odoo/addons/sale_stock_release_channel/static/description/icon.png
odoo/addons/sale_stock_release_channel/static/description/index.html
odoo/addons/sale_stock_release_channel/tests/__init__.py
odoo/addons/sale_stock_release_channel/tests/common.py
odoo/addons/sale_stock_release_channel/tests/test_release_channel.py
odoo_addon_sale_stock_release_channel-18.0.1.0.1.dist-info/METADATA
odoo_addon_sale_stock_release_channel-18.0.1.0.1.dist-info/WHEEL
odoo_addon_sale_stock_release_channel-18.0.1.0.1.dist-info/top_level.txt
odoo_addon_sale_stock_release_channel-18.0.1.0.1.dist-info/RECORD
